{
  "lat": 51.5073,
  "lon": -0.1276,
  "timezone": "Europe/London",
  "timezone_offset": 3600,
  "current": {
    "dt": 1755143812,
    "sunrise": 1755146678,
    "sunset": 1755199557,
    "temp": 18.06,
    "feels_like": 18.09,
    "pressure": 1016,
    "humidity": 83,
    "dew_point": 15.13,
    "uvi": 0,
    "clouds": 100,
    "visibility": 10000,
    "wind_speed": 4.12,
    "wind_deg": 240,
    "weather": [
      {
        "id": 804,
        "main": "Clouds",
        "description": "overcast clouds",
        "icon": "04n"
      }
    ]
  },
  "hourly": [
    {
      "dt": 1755140400,
      "temp": 17.84,
      "feels_like": 17.87,
      "pressure": 1016,
      "humidity": 84,
      "dew_point": 15.1,
      "uvi": 0,
      "clouds": 85,
      "visibility": 10000,
      "wind_speed": 2.36,
      "wind_deg": 234,
      "wind_gust": 6.53,
      "weather": [
        {
          "id": 804,
          "main": "Clouds",
          "description": "overcast clouds",
          "icon": "04n"
        }
      ],
      "pop": 0.22
    },
    {
      "dt": 1755144000,
      "temp": 18.06,
      "feels_like": 18.09,
      "pressure": 1016,
      "humidity": 83,
      "dew_point": 15.13,
      "uvi": 0,
      "clouds": 100,
      "visibility": 10000,
      "wind_speed": 2.29,
      "wind_deg": 235,
      "wind_gust": 6.49,
      "weather": [
        {
          "id": 804,
          "main": "Clouds",
          "description": "overcast clouds",
          "icon": "04n"
        }
      ],
      "pop": 0.06
    },
    {
      "dt": 1755309600,
      "temp": 18.71,
      "feels_like": 18.57,
      "pressure": 1026,
      "humidity": 74,
      "dew_point": 13.71,
      "uvi": 0,
      "clouds": 25,
      "visibility": 10000,
      "wind_speed": 3.68,
      "wind_deg": 68,
      "wind_gust": 7.45,
      "weather": [
        {
          "id": 802,
          "main": "Clouds",
          "description": "scattered clouds",
          "icon": "03n"
        }
      ],
      "pop": 0
    }
  ],
  "alerts": [
    {
      "sender_name": "NWS Philadelphia - Mount Holly (New Jersey, Delaware, Southeastern Pennsylvania)",
      "event": "Small Craft Advisory",
      "start": 1684952747,
      "end": 1684988747,
      "description": "...SMALL CRAFT ADVISORY REMAINS IN EFFECT FROM 5 PM THIS\nAFTERNOON TO 3 AM EST FRIDAY...\n* WHAT...North winds 15 to 20 kt with gusts up to 25 kt and seas\n3 to 5 ft expected.\n* WHERE...Coastal waters from Little Egg Inlet to Great Egg\nInlet NJ out 20 nm, Coastal waters from Great Egg Inlet to\nCape May NJ out 20 nm and Coastal waters from Manasquan Inlet\nto Little Egg Inlet NJ out 20 nm.\n* WHEN...From 5 PM this afternoon to 3 AM EST Friday.\n* IMPACTS...Conditions will be hazardous to small craft.",
      "tags": [
      ]
    }
  ]
}